[{"ENTITY_1": "Vitamin Shoppe", "CONNECTION": "manufactures", "ENTITY_2": "Ultimate 10 Probiotic"}, {"ENTITY_1": "Ultimate 10 Probiotic", "CONNECTION": "supports", "ENTITY_2": "Digestive Health"}, {"ENTITY_1": "Ultimate 10 Probiotic", "CONNECTION": "supports", "ENTITY_2": "Intestinal Health"}, {"ENTITY_1": "Ultimate 10 Probiotic", "CONNECTION": "supports", "ENTITY_2": "Immunity"}, {"ENTITY_1": "Ultimate 10 Probiotic", "CONNECTION": "contains", "ENTITY_2": "13 Billion Bacteria"}, {"ENTITY_1": "Ultimate 10 Probiotic", "CONNECTION": "requires", "ENTITY_2": "No Refrigeration"}, {"ENTITY_1": "Ultimate 10 Probiotic", "CONNECTION": "has", "ENTITY_2": "100 Capsules"}, {"ENTITY_1": "Ultimate 10 Probiotic", "CONNECTION": "has", "ENTITY_2": "61 Ratings"}]