[{"ENTITY_1": "Pharmacist", "CONNECTION": "understands", "ENTITY_2": "product"}, {"ENTITY_1": "Pharmacist", "CONNECTION": "bought", "ENTITY_2": "product"}, {"ENTITY_1": "Pharmacist", "CONNECTION": "suffers from", "ENTITY_2": "GERD"}, {"ENTITY_1": "Pharmacist", "CONNECTION": "suffers from", "ENTITY_2": "IBS"}, {"ENTITY_1": "Pharmacist", "CONNECTION": "takes", "ENTITY_2": "ompeprazole"}, {"ENTITY_1": "Pharmacist", "CONNECTION": "knows", "ENTITY_2": "digestion compromised"}, {"ENTITY_1": "Pharmacist", "CONNECTION": "suggests", "ENTITY_2": "enzyme supplement should help"}, {"ENTITY_1": "Pharmacist", "CONNECTION": "received", "ENTITY_2": "old lot"}, {"ENTITY_1": "Pharmacist", "CONNECTION": "received", "ENTITY_2": "improperly stored lot"}, {"ENTITY_1": "Pharmacist", "CONNECTION": "cannot recommend", "ENTITY_2": "product"}]