[{"ENTITY_1": "fake reviews", "CONNECTION": "scared away", "ENTITY_2": "product"}, {"ENTITY_1": "product", "CONNECTION": "returned", "ENTITY_2": "buyer"}, {"ENTITY_1": "multivitamin", "CONNECTION": "is", "ENTITY_2": "great"}, {"ENTITY_1": "multivitamin", "CONNECTION": "is", "ENTITY_2": "natural"}, {"ENTITY_1": "multivitamin", "CONNECTION": "is", "ENTITY_2": "effective"}, {"ENTITY_1": "multivitamin", "CONNECTION": "is", "ENTITY_2": "easy to swallow"}, {"ENTITY_1": "multivitamin", "CONNECTION": "is", "ENTITY_2": "good value"}, {"ENTITY_1": "multivitamin", "CONNECTION": "is", "ENTITY_2": "balanced"}, {"ENTITY_1": "multivitamin", "CONNECTION": "is", "ENTITY_2": "fast shipping"}, {"ENTITY_1": "multivitamin", "CONNECTION": "is", "ENTITY_2": "highly recommended"}, {"ENTITY_1": "multivitamin", "CONNECTION": "is", "ENTITY_2": "important for health"}]