[{"ENTITY_1": "Globe Pharmacy", "CONNECTION": "is manufactured by", "ENTITY_2": "Trifecta Pharmaceuticals USA"}, {"ENTITY_1": "Globe Pharmacy", "CONNECTION": "has ASIN", "ENTITY_2": "B073FPLBNL"}, {"ENTITY_1": "Globe Pharmacy", "CONNECTION": "has brand", "ENTITY_2": "Globe Pharmacy"}, {"ENTITY_1": "Globe Pharmacy", "CONNECTION": "has number of ratings", "ENTITY_2": "179"}, {"ENTITY_1": "Globe Pharmacy", "CONNECTION": "has average rating", "ENTITY_2": "4.3"}, {"ENTITY_1": "Globe Pharmacy", "CONNECTION": "has item title", "ENTITY_2": "2 PACK Hemorrhoidal Cooling Gel For Fast Relief With Vitamin E And Aloe Tube (2 X 1.8 OZ TUBES) COMPARE TO PREPARATION H COOLING GEL"}]