[{"ENTITY_1": "Nevissbags", "CONNECTION": "is manufacturer of", "ENTITY_2": "Organic Black Elderberry Gummies"}, {"ENTITY_1": "Organic Black Elderberry Gummies", "CONNECTION": "has average rating of", "ENTITY_2": "3.2"}, {"ENTITY_1": "Nevissbags", "CONNECTION": "is brand of", "ENTITY_2": "Organic Black Elderberry Gummies"}, {"ENTITY_1": "Organic Black Elderberry Gummies", "CONNECTION": "has number of ratings of", "ENTITY_2": "14"}, {"ENTITY_1": "Organic Black Elderberry Gummies", "CONNECTION": "has user rating of", "ENTITY_2": "1.0"}, {"ENTITY_1": "Organic Black Elderberry Gummies", "CONNECTION": "has user rating of", "ENTITY_2": "4.0"}]