[{"ENTITY_1": "Celebrate Vitamins", "CONNECTION": "manufactured by", "ENTITY_2": "Celebrate Vitamins"}, {"ENTITY_1": "Celebrate Vitamins", "CONNECTION": "has average rating", "ENTITY_2": "4.2"}, {"ENTITY_1": "Celebrate Vitamins", "CONNECTION": "has number of ratings", "ENTITY_2": "341"}, {"ENTITY_1": "Celebrate Vitamins", "CONNECTION": "has item form", "ENTITY_2": "Tablet, Chewable"}, {"ENTITY_1": "Celebrate Vitamins", "CONNECTION": "has manufacturer", "ENTITY_2": "Celebrate Vitamins"}, {"ENTITY_1": "Celebrate Vitamins", "CONNECTION": "has title", "ENTITY_2": "Celebrate Vitamins Calcium Citrate Soft Chews - 500 mg - Island Fruit - 90 Count"}]