[{"ENTITY_1": "myPEAK Wellness", "CONNECTION": "manufactured by", "ENTITY_2": "AZZUTORK"}, {"ENTITY_1": "myPEAK Wellness", "CONNECTION": "contains", "ENTITY_2": "Alpha-GPC"}, {"ENTITY_1": "myPEAK Wellness", "CONNECTION": "contains", "ENTITY_2": "Resveratrol"}, {"ENTITY_1": "myPEAK Wellness", "CONNECTION": "contains", "ENTITY_2": "Astaxanthin"}, {"ENTITY_1": "myPEAK Wellness", "CONNECTION": "contains", "ENTITY_2": "ElevATP"}, {"ENTITY_1": "myPEAK Wellness", "CONNECTION": "recommended by", "ENTITY_2": "AHH7DYW535JNEGASCET44RLTKG7A"}, {"ENTITY_1": "myPEAK Wellness", "CONNECTION": "recommended by", "ENTITY_2": "AGNUU44ETNXLBOUB53LJGFJP3SQA"}, {"ENTITY_1": "myPEAK Wellness", "CONNECTION": "recommended by", "ENTITY_2": "AHRIATJC7EKLNLLBEXY4WAMENRZQ"}, {"ENTITY_1": "myPEAK Wellness", "CONNECTION": "recommended by", "ENTITY_2": "AFVOZ4UNUZKEQ7GTQ3IHQY7PZ5FA_1"}]