[{"ENTITY_1": "Steel Bite Pro", "CONNECTION": "has average rating", "ENTITY_2": "3.8"}, {"ENTITY_1": "Steel Bite Pro", "CONNECTION": "has number of ratings", "ENTITY_2": "71"}, {"ENTITY_1": "Steel Bite Pro", "CONNECTION": "is manufactured by", "ENTITY_2": "Steel Bite"}, {"ENTITY_1": "Steel Bite Pro", "CONNECTION": "is a dental supplement", "ENTITY_2": "Capsule"}, {"ENTITY_1": "Steel Bite Pro", "CONNECTION": "is a dental care product", "ENTITY_2": "Oral Care Products"}, {"ENTITY_1": "Steel Bite Pro", "CONNECTION": "is a brand of", "ENTITY_2": "Medix"}]