[{"ENTITY_1": "AHJYOD56GVUHGUW6NV4US7JR6NDA", "CONNECTION": "reviewed", "ENTITY_2": "B08SRD6BYC"}, {"ENTITY_1": "B08SRD6BYC", "CONNECTION": "has", "ENTITY_2": "Average Rating: 4.3"}, {"ENTITY_1": "B08SRD6BYC", "CONNECTION": "has", "ENTITY_2": "Number of Ratings: 25"}, {"ENTITY_1": "B08SRD6BYC", "CONNECTION": "is", "ENTITY_2": "KIKI Green Active Hexose Correlated Compound"}, {"ENTITY_1": "KIKI Green Active Hexose Correlated Compound", "CONNECTION": "is", "ENTITY_2": "Immune Support Supplement"}, {"ENTITY_1": "KIKI Green Active Hexose Correlated Compound", "CONNECTION": "is", "ENTITY_2": "1000mg Per Serving"}]