[{"ENTITY_1": "Apple Cider Vinegar Gummies", "CONNECTION": "incorporate", "ENTITY_2": "diets"}, {"ENTITY_1": "Apple Cider Vinegar Gummies", "CONNECTION": "taste", "ENTITY_2": "good"}, {"ENTITY_1": "Apple Cider Vinegar Gummies", "CONNECTION": "effective", "ENTITY_2": "yes"}, {"ENTITY_1": "Apple Cider Vinegar Gummies", "CONNECTION": "contain", "ENTITY_2": "natural ingredients"}, {"ENTITY_1": "Apple Cider Vinegar Gummies", "CONNECTION": "smell", "ENTITY_2": "chemical"}, {"ENTITY_1": "Apple Cider Vinegar Gummies", "CONNECTION": "contain", "ENTITY_2": "sugar"}, {"ENTITY_1": "Apple Cider Vinegar Gummies", "CONNECTION": "contain", "ENTITY_2": "Pomegranate"}, {"ENTITY_1": "Apple Cider Vinegar Gummies", "CONNECTION": "contain", "ENTITY_2": "Beetroot"}, {"ENTITY_1": "Apple Cider Vinegar Gummies", "CONNECTION": "contain", "ENTITY_2": "Vitamin B12"}, {"ENTITY_1": "Apple Cider Vinegar Gummies", "CONNECTION": "made in", "ENTITY_2": "USA"}, {"ENTITY_1": "Apple Cider Vinegar Gummies", "CONNECTION": "price", "ENTITY_2": "high"}]